LICENSE
MANIFEST.in
README.md
VERSION
setup.cfg
setup.py
obob_mne/__init__.py
obob_mne/epochs.py
obob_mne/events.py
obob_mne/raw.py
obob_mne.egg-info/PKG-INFO
obob_mne.egg-info/SOURCES.txt
obob_mne.egg-info/dependency_links.txt
obob_mne.egg-info/entry_points.txt
obob_mne.egg-info/requires.txt
obob_mne.egg-info/top_level.txt
obob_mne/decoding/__init__.py
obob_mne/decoding/gentemporal.py
obob_mne/decoding/helpers.py
obob_mne/decoding/temporal.py
obob_mne/mixins/__init__.py
obob_mne/mixins/raw.py
obob_mne/mri/__init__.py
obob_mne/mri/cmd/__init__.py
obob_mne/mri/cmd/import_subject.py
obob_mne/mri/cmd/make_freesurfer_bem.py
obob_mne/mri/cmd/make_source_space.py
obob_mne/mri/cmd/utils/__init__.py
obob_mne/mri/cmd/utils/jobs.py
tests/__init__.py
tests/test_example.py