Metadata-Version: 2.1
Name: obob-mne
Version: 0.0.16
Summary: I am obob_mne
Home-page: https://gitlab.com/obob/obob_mne
Author: Thomas Hartmann
Author-email: thomas.hartmann@th-ht.de
License: GPL3
Platform: UNKNOWN
License-File: LICENSE
